{"cameraMode":{"drawMode":2,"name":"Shaded Wireframe","section":"Shading Mode"},"sceneLighting":false,"audioPlay":false,"sceneViewState":{"m_AlwaysRefresh":false,"showFog":true,"showSkybox":false,"showFlares":true,"showImageEffects":true,"showParticleSystems":true,"showVisualEffectGraphs":true,"m_FxEnabled":true},"in2DMode":false,"pivot":{"x":19.360000610351564,"y":4.960000038146973,"z":24.38360023498535},"rotation":{"x":0.042262203991413119,"y":-0.9537777304649353,"z":0.2501557469367981,"w":0.16117127239704133},"size":12.871428489685059,"orthographic":true}